{
    "kind":"analytics#gaData",
    "id":"https://www.googleapis.com/analytics/v3/data/ga?ids=ga:56580952&dimensions=ga:eventCategory,ga:eventAction,ga:eventLabel&metrics=ga:totalEvents&filters=ga:eventCategory%3D~%5EMS_.*&start-date=2013-01-13&end-date=2013-01-19&start-index=6&max-results=5",
    "query":{
        "start-date":"2013-01-13",
        "end-date":"2013-01-19",
        "ids":"ga:56580952",
        "dimensions":"ga:eventCategory,ga:eventAction,ga:eventLabel",
        "metrics":["ga:totalEvents"],
        "filters":"ga:eventCategory=~^MS_.*",
        "start-index":6,
        "max-results":5
    },
    "itemsPerPage":5,
    "totalResults":9,
    "selfLink":"https://www.googleapis.com/analytics/v3/data/ga?ids=ga:56580952&dimensions=ga:eventCategory,ga:eventAction,ga:eventLabel&metrics=ga:totalEvents&filters=ga:eventCategory%3D~%5EMS_.*&start-date=2013-01-13&end-date=2013-01-19&start-index=6&max-results=5",
    "previousLink":"https://www.googleapis.com/analytics/v3/data/ga?ids=ga:56580952&dimensions=ga:eventCategory,ga:eventAction,ga:eventLabel&metrics=ga:totalEvents&filters=ga:eventCategory%3D~%5EMS_.*&start-date=2013-01-13&end-date=2013-01-19&start-index=1&max-results=5",
    "profileInfo":{
        "profileId":"56580952",
        "accountId":"26179049",
        "webPropertyId":"UA-26179049-1",
        "internalWebPropertyId":"50705554",
        "profileName":"1. GOV.UK (Entire site - Filtered)",
        "tableId":"ga:56580952"
    },
    "containsSampledData":false,
    "columnHeaders":[
        {
            "name":"ga:eventCategory",
            "columnType":"DIMENSION",
            "dataType":"STRING"
        },
        {
            "name":"ga:eventAction",
            "columnType":"DIMENSION",
            "dataType":"STRING"
        },
        {
            "name":"ga:eventLabel",
            "columnType":"DIMENSION",
            "dataType":"STRING"
        },
        {
            "name":"ga:totalEvents",
            "columnType":"METRIC",
            "dataType":"INTEGER"
        }
    ],
    "totalsForAllResults":{
        "ga:totalEvents":"5210"
    },
    "rows":[
        ["MS_answer", "1884", "Success", "2"],
        ["MS_answer", "1993", "Entry", "1"],
        ["MS_answer", "1993", "Success", "1"],
        ["MS_answer", "2183", "Success", "20"]
    ]
}
